pyBusPirateLite/BitBang.py
pyBusPirateLite/I2C.py
pyBusPirateLite/I2Chigh.py
pyBusPirateLite/SPI.py
pyBusPirateLite/UART.py
pyBusPirateLite/UC.py
pyBusPirateLite/__init__.py
pyBusPirateLite/base.py
pyBusPirateLite/common_functions.py
pyBusPirateLite/onewire.py
pyBusPirateLite/rawwire.py
pybuspiratelite-0.1.0.dist-info/METADATA
pybuspiratelite-0.1.0.dist-info/WHEEL
pybuspiratelite-0.1.0.dist-info/licenses/LICENSE
pybuspiratelite-0.1.0.dist-info/RECORD
