Metadata-Version: 2.1
Name: pyBusPirateLite
Version: 0.1.0
Summary: A Python driver for Bus Pirate
Project-URL: Homepage, https://github.com/zapta/pyBusPirateLite
Project-URL: Bug Tracker, https://github.com/zapta/pyBusPirateLite/issues
Author-email: Zapta <zapta@zapta.com>
License-File: LICENSE
Classifier: License :: OSI Approved :: GNU General Public License v3 (GPLv3)
Classifier: Operating System :: OS Independent
Classifier: Programming Language :: Python :: 3
Requires-Python: >=3.7
Requires-Dist: serial>=0.0.97
